[
  { "name": "Algarve International Circuit", "country": "PT", "city": "Portimão", "type": "PERMANENT", "lengthKm": 4.653, "turns": 15, "openedYear": 2008 },
  { "name": "Autodromo Hermanos Rodríguez", "country": "MX", "city": "Mexico City", "type": "PERMANENT", "lengthKm": 4.304, "turns": 17, "openedYear": 1959 },
  { "name": "Autodromo Internazionale Enzo e Dino Ferrari", "country": "IT", "city": "Imola", "type": "PERMANENT", "lengthKm": 4.909, "turns": 19, "openedYear": 1953 },
  { "name": "Autodromo Nazionale Monza", "country": "IT", "city": "Monza", "type": "PERMANENT", "lengthKm": 5.793, "turns": 11, "openedYear": 1922 },
  { "name": "Autódromo José Carlos Pace", "country": "BR", "city": "São Paulo", "type": "PERMANENT", "lengthKm": 4.309, "turns": 15, "openedYear": 1940 },
  { "name": "Bahrain International Circuit", "country": "BH", "city": "Sakhir", "type": "PERMANENT", "lengthKm": 5.412, "turns": 15, "openedYear": 2004 },
  { "name": "Barber Motorsports Park", "country": "US", "city": "Birmingham", "type": "PERMANENT", "lengthKm": 3.83, "turns": 17, "openedYear": 2003 },
  { "name": "Brands Hatch", "country": "GB", "city": "Kent", "type": "PERMANENT", "lengthKm": 3.908, "turns": 9, "openedYear": 1950 },
  { "name": "Buddh International Circuit", "country": "IN", "city": "Greater Noida", "type": "PERMANENT", "lengthKm": 5.125, "turns": 16, "openedYear": 2011 },
  { "name": "Circuit de Barcelona-Catalunya", "country": "ES", "city": "Barcelona", "type": "PERMANENT", "lengthKm": 4.657, "turns": 16, "openedYear": 1991 },
  { "name": "Circuit de la Sarthe", "country": "FR", "city": "Le Mans", "type": "ROAD", "lengthKm": 13.626, "turns": 38, "openedYear": 1923 },
  { "name": "Circuit de Monaco", "country": "MC", "city": "Monte Carlo", "type": "STREET", "lengthKm": 3.337, "turns": 19, "openedYear": 1929 },
  { "name": "Circuit de Nevers Magny-Cours", "country": "FR", "city": "Magny-Cours", "type": "PERMANENT", "lengthKm": 4.411, "turns": 17, "openedYear": 1960 },
  { "name": "Circuit de Spa-Francorchamps", "country": "BE", "city": "Stavelot", "type": "PERMANENT", "lengthKm": 7.004, "turns": 19, "openedYear": 1921 },
  { "name": "Circuit Gilles Villeneuve", "country": "CA", "city": "Montréal", "type": "STREET", "lengthKm": 4.361, "turns": 14, "openedYear": 1978 },
  { "name": "Circuit of the Americas", "country": "US", "city": "Austin", "type": "PERMANENT", "lengthKm": 5.513, "turns": 20, "openedYear": 2012 },
  { "name": "Circuit Paul Ricard", "country": "FR", "city": "Le Castellet", "type": "PERMANENT", "lengthKm": 5.842, "turns": 15, "openedYear": 1970 },
  { "name": "Circuit Ricardo Tormo", "country": "ES", "city": "Cheste", "type": "PERMANENT", "lengthKm": 4.005, "turns": 14, "openedYear": 1999 },
  { "name": "Circuit Zandvoort", "country": "NL", "city": "Zandvoort", "type": "PERMANENT", "lengthKm": 4.259, "turns": 14, "openedYear": 1948 },
  { "name": "Circuit Zolder", "country": "BE", "city": "Heusden-Zolder", "type": "PERMANENT", "lengthKm": 4.011, "turns": 10, "openedYear": 1963 },
  { "name": "Daytona International Speedway", "country": "US", "city": "Daytona Beach", "type": "OVAL", "lengthKm": 5.729, "openedYear": 1959 },
  { "name": "Donington Park", "country": "GB", "city": "Castle Donington", "type": "PERMANENT", "lengthKm": 4.02, "turns": 12, "openedYear": 1931 },
  { "name": "Dubai Autodrome", "country": "AE", "city": "Dubai", "type": "PERMANENT", "lengthKm": 5.39, "turns": 16, "openedYear": 2004 },
  { "name": "Fuji Speedway", "country": "JP", "city": "Oyama", "type": "PERMANENT", "lengthKm": 4.563, "turns": 16, "openedYear": 1966 },
  { "name": "Hockenheimring", "country": "DE", "city": "Hockenheim", "type": "PERMANENT", "lengthKm": 4.574, "turns": 17, "openedYear": 1932 },
  { "name": "Hungaroring", "country": "HU", "city": "Mogyoród", "type": "PERMANENT", "lengthKm": 4.381, "turns": 14, "openedYear": 1986 },
  { "name": "Indianapolis Motor Speedway", "country": "US", "city": "Speedway", "type": "OVAL", "lengthKm": 4.023, "openedYear": 1909 },
  { "name": "Jeddah Corniche Circuit", "country": "SA", "city": "Jeddah", "type": "STREET", "lengthKm": 6.174, "turns": 27, "openedYear": 2021 },
  { "name": "Kyalami Grand Prix Circuit", "country": "ZA", "city": "Midrand", "type": "PERMANENT", "lengthKm": 4.522, "turns": 16, "openedYear": 1961 },
  { "name": "Lausitzring", "country": "DE", "city": "Klettwitz", "type": "PERMANENT", "openedYear": 2000 },
  { "name": "Long Beach Street Circuit", "country": "US", "city": "Long Beach", "type": "STREET", "lengthKm": 3.167, "turns": 11, "openedYear": 1975 },
  { "name": "Losail International Circuit", "country": "QA", "city": "Lusail", "type": "PERMANENT", "lengthKm": 5.419, "turns": 16, "openedYear": 2004 },
  { "name": "Marina Bay Street Circuit", "country": "SG", "city": "Singapore", "type": "STREET", "lengthKm": 4.94, "turns": 19, "openedYear": 2008 },
  { "name": "Michelin Raceway Road Atlanta", "country": "US", "city": "Braselton", "type": "PERMANENT", "lengthKm": 4.088, "turns": 12, "openedYear": 1970 },
  { "name": "Misano World Circuit Marco Simoncelli", "country": "IT", "city": "Misano Adriatico", "type": "PERMANENT", "lengthKm": 4.226, "turns": 16, "openedYear": 1972 },
  { "name": "Mobility Resort Motegi", "country": "JP", "city": "Motegi", "type": "PERMANENT", "lengthKm": 4.801, "turns": 14, "openedYear": 1997 },
  { "name": "Mount Panorama Circuit", "country": "AU", "city": "Bathurst", "type": "ROAD", "lengthKm": 6.213, "turns": 23, "openedYear": 1938 },
  { "name": "Mugello Circuit", "country": "IT", "city": "Scarperia", "type": "PERMANENT", "lengthKm": 5.245, "turns": 15, "openedYear": 1974 },
  { "name": "Nürburgring", "country": "DE", "city": "Nürburg", "type": "PERMANENT", "lengthKm": 5.148, "turns": 15, "openedYear": 1927 },
  { "name": "Nürburgring Nordschleife", "country": "DE", "city": "Nürburg", "type": "ROAD", "lengthKm": 20.832, "turns": 154, "openedYear": 1927 },
  { "name": "Oulton Park", "country": "GB", "city": "Little Budworth", "type": "PERMANENT", "lengthKm": 4.307, "turns": 16, "openedYear": 1953 },
  { "name": "Phillip Island Grand Prix Circuit", "country": "AU", "city": "Phillip Island", "type": "PERMANENT", "lengthKm": 4.445, "turns": 12, "openedYear": 1956 },
  { "name": "Red Bull Ring", "country": "AT", "city": "Spielberg", "type": "PERMANENT", "lengthKm": 4.318, "turns": 10, "openedYear": 1969 },
  { "name": "Road America", "country": "US", "city": "Elkhart Lake", "type": "PERMANENT", "lengthKm": 6.515, "turns": 14, "openedYear": 1955 },
  { "name": "Sebring International Raceway", "country": "US", "city": "Sebring", "type": "PERMANENT", "lengthKm": 6.019, "turns": 17, "openedYear": 1950 },
  { "name": "Sepang International Circuit", "country": "MY", "city": "Sepang", "type": "PERMANENT", "lengthKm": 5.543, "turns": 15, "openedYear": 1999 },
  { "name": "Shanghai International Circuit", "country": "CN", "city": "Shanghai", "type": "PERMANENT", "lengthKm": 5.451, "turns": 16, "openedYear": 2004 },
  { "name": "Silverstone Circuit", "country": "GB", "city": "Silverstone", "type": "PERMANENT", "lengthKm": 5.891, "turns": 18, "openedYear": 1948 },
  { "name": "Sochi Autodrom", "country": "RU", "city": "Sochi", "type": "STREET", "lengthKm": 5.848, "turns": 18, "openedYear": 2014 },
  { "name": "Sonoma Raceway", "country": "US", "city": "Sonoma", "type": "PERMANENT", "lengthKm": 4.05, "turns": 12, "openedYear": 1968 },
  { "name": "Suzuka International Racing Course", "country": "JP", "city": "Suzuka", "type": "PERMANENT", "lengthKm": 5.807, "turns": 18, "openedYear": 1962 },
  { "name": "TT Circuit Assen", "country": "NL", "city": "Assen", "type": "PERMANENT", "lengthKm": 4.542, "turns": 18, "openedYear": 1955 },
  { "name": "Vallelunga Circuit", "country": "IT", "city": "Campagnano di Roma", "type": "PERMANENT", "lengthKm": 4.085, "turns": 14, "openedYear": 1951 },
  { "name": "Virginia International Raceway", "country": "US", "city": "Alton", "type": "PERMANENT", "lengthKm": 5.262, "turns": 17, "openedYear": 1957 },
  { "name": "Watkins Glen International", "country": "US", "city": "Watkins Glen", "type": "PERMANENT", "lengthKm": 5.552, "turns": 11, "openedYear": 1956 },
  { "name": "WeatherTech Raceway Laguna Seca", "country": "US", "city": "Monterey", "type": "PERMANENT", "lengthKm": 3.602, "turns": 11, "openedYear": 1957 },
  { "name": "Yas Marina Circuit", "country": "AE", "city": "Abu Dhabi", "type": "PERMANENT", "lengthKm": 5.281, "turns": 16, "openedYear": 2009 },
  { "name": "Adelaide Street Circuit", "country": "AU", "city": "Adelaide", "type": "STREET" },
  { "name": "Adria International Raceway", "country": "IT", "city": "Adria", "type": "PERMANENT" },
  { "name": "Ahvenisto Race Circuit", "country": "FI", "city": "Hämeenlinna", "type": "PERMANENT" },
  { "name": "Alastaro Circuit", "country": "FI", "city": "Alastaro", "type": "PERMANENT" },
  { "name": "Albert Park Circuit", "country": "AU", "city": "Melbourne", "type": "STREET", "lengthKm": 5.278, "turns": 14, "openedYear": 1996 },
  { "name": "Anderstorp Raceway", "country": "SE", "city": "Anderstorp", "type": "PERMANENT", "openedYear": 1968 },
  { "name": "Anglesey Circuit", "country": "GB", "city": "Anglesey", "type": "PERMANENT" },
  { "name": "Ascari Race Resort", "country": "ES", "city": "Ronda", "type": "PERMANENT" },
  { "name": "Atlanta Motor Speedway", "country": "US", "city": "Hampton", "type": "OVAL" },
  { "name": "Autodrom Most", "country": "CZ", "city": "Most", "type": "PERMANENT" },
  { "name": "Automotodrom Brno", "country": "CZ", "city": "Brno", "type": "PERMANENT", "lengthKm": 5.403, "openedYear": 1987 },
  { "name": "Autódromo do Estoril", "country": "PT", "city": "Estoril", "type": "PERMANENT", "lengthKm": 4.182, "openedYear": 1972 },
  { "name": "Autódromo Internacional de Curitiba", "country": "BR", "city": "Pinhais", "type": "PERMANENT" },
  { "name": "Autódromo Internacional de Goiânia", "country": "BR", "city": "Goiânia", "type": "PERMANENT" },
  { "name": "Autódromo Internacional Nelson Piquet", "country": "BR", "city": "Brasília", "type": "PERMANENT" },
  { "name": "Autódromo Oscar Cabalén", "country": "AR", "city": "Alta Gracia", "type": "PERMANENT" },
  { "name": "Autódromo Oscar y Juan Gálvez", "country": "AR", "city": "Buenos Aires", "type": "PERMANENT" },
  { "name": "Autódromo Termas de Río Hondo", "country": "AR", "city": "Termas de Río Hondo", "type": "PERMANENT", "lengthKm": 4.806, "openedYear": 2008 },
  { "name": "Autódromo Velo Città", "country": "BR", "city": "Mogi Guaçu", "type": "PERMANENT" },
  { "name": "Autódromo Víctor Borrat Fabini", "country": "UY", "city": "El Pinar", "type": "PERMANENT" },
  { "name": "Autodromo di Pergusa", "country": "IT", "city": "Enna", "type": "PERMANENT" },
  { "name": "Autodromo Riccardo Paletti", "country": "IT", "city": "Varano de' Melegari", "type": "PERMANENT" },
  { "name": "Autopolis", "country": "JP", "city": "Hita", "type": "PERMANENT" },
  { "name": "Bilster Berg", "country": "DE", "city": "Bad Driburg", "type": "PERMANENT" },
  { "name": "Brainerd International Raceway", "country": "US", "city": "Brainerd", "type": "PERMANENT" },
  { "name": "Bristol Motor Speedway", "country": "US", "city": "Bristol", "type": "OVAL" },
  { "name": "Bugatti Circuit", "country": "FR", "city": "Le Mans", "type": "PERMANENT", "lengthKm": 4.185, "openedYear": 1965 },
  { "name": "Cadwell Park", "country": "GB", "city": "Louth", "type": "PERMANENT" },
  { "name": "Canadian Tire Motorsport Park", "country": "CA", "city": "Bowmanville", "type": "PERMANENT", "lengthKm": 3.957, "openedYear": 1961 },
  { "name": "Castle Combe Circuit", "country": "GB", "city": "Chippenham", "type": "PERMANENT" },
  { "name": "Chang International Circuit", "country": "TH", "city": "Buriram", "type": "PERMANENT", "lengthKm": 4.554, "openedYear": 2014 },
  { "name": "Charlotte Motor Speedway", "country": "US", "city": "Concord", "type": "OVAL" },
  { "name": "Circuit de Charade", "country": "FR", "city": "Clermont-Ferrand", "type": "PERMANENT" },
  { "name": "Circuit de Lédenon", "country": "FR", "city": "Lédenon", "type": "PERMANENT" },
  { "name": "Circuit de Mettet", "country": "BE", "city": "Mettet", "type": "PERMANENT" },
  { "name": "Circuit de Pau-Ville", "country": "FR", "city": "Pau", "type": "STREET" },
  { "name": "Circuit Dijon-Prenois", "country": "FR", "city": "Dijon", "type": "PERMANENT", "openedYear": 1972 },
  { "name": "Circuit du Val de Vienne", "country": "FR", "city": "Le Vigeant", "type": "PERMANENT" },
  { "name": "Circuit Mont-Tremblant", "country": "CA", "city": "Mont-Tremblant", "type": "PERMANENT" },
  { "name": "Circuit Paul Armagnac", "country": "FR", "city": "Nogaro", "type": "PERMANENT" },
  { "name": "Circuit Trois-Rivières", "country": "CA", "city": "Trois-Rivières", "type": "STREET" },
  { "name": "Circuito de Albacete", "country": "ES", "city": "Albacete", "type": "PERMANENT" },
  { "name": "Circuito de Jerez", "country": "ES", "city": "Jerez de la Frontera", "type": "PERMANENT", "lengthKm": 4.428, "openedYear": 1985 },
  { "name": "Circuito de Navarra", "country": "ES", "city": "Los Arcos", "type": "PERMANENT" },
  { "name": "Circuito de Vila Real", "country": "PT", "city": "Vila Real", "type": "STREET" },
  { "name": "Circuito del Jarama", "country": "ES", "city": "San Sebastián de los Reyes", "type": "PERMANENT", "openedYear": 1967 },
  { "name": "Circuito San Juan Villicum", "country": "AR", "city": "San Juan", "type": "PERMANENT" },
  { "name": "Croft Circuit", "country": "GB", "city": "Darlington", "type": "PERMANENT" },
  { "name": "Darlington Raceway", "country": "US", "city": "Darlington", "type": "OVAL" },
  { "name": "Dover Motor Speedway", "country": "US", "city": "Dover", "type": "OVAL" },
  { "name": "Goldenport Park Circuit", "country": "CN", "city": "Beijing", "type": "PERMANENT" },
  { "name": "Goodwood Circuit", "country": "GB", "city": "Chichester", "type": "PERMANENT", "openedYear": 1948 },
  { "name": "Hampton Downs Motorsport Park", "country": "NZ", "city": "Waikato", "type": "PERMANENT" },
  { "name": "Highlands Motorsport Park", "country": "NZ", "city": "Cromwell", "type": "PERMANENT" },
  { "name": "Homestead-Miami Speedway", "country": "US", "city": "Homestead", "type": "OVAL" },
  { "name": "Igora Drive", "country": "RU", "city": "Saint Petersburg", "type": "PERMANENT" },
  { "name": "Inje Speedium", "country": "KR", "city": "Inje", "type": "PERMANENT" },
  { "name": "Istanbul Park", "country": "TR", "city": "Istanbul", "type": "PERMANENT", "lengthKm": 5.338, "turns": 14, "openedYear": 2005 },
  { "name": "Iowa Speedway", "country": "US", "city": "Newton", "type": "OVAL" },
  { "name": "Jyllandsringen", "country": "DK", "city": "Silkeborg", "type": "PERMANENT" },
  { "name": "Kansas Speedway", "country": "US", "city": "Kansas City", "type": "OVAL" },
  { "name": "Kari Motor Speedway", "country": "IN", "city": "Coimbatore", "type": "PERMANENT" },
  { "name": "Killarney International Raceway", "country": "ZA", "city": "Cape Town", "type": "PERMANENT" },
  { "name": "Knockhill Racing Circuit", "country": "GB", "city": "Fife", "type": "PERMANENT" },
  { "name": "Korea International Circuit", "country": "KR", "city": "Yeongam", "type": "PERMANENT", "lengthKm": 5.615, "openedYear": 2010 },
  { "name": "Las Vegas Motor Speedway", "country": "US", "city": "Las Vegas", "type": "OVAL" },
  { "name": "Lime Rock Park", "country": "US", "city": "Lakeville", "type": "PERMANENT" },
  { "name": "Madras International Circuit", "country": "IN", "city": "Chennai", "type": "PERMANENT" },
  { "name": "Mallory Park", "country": "GB", "city": "Leicestershire", "type": "PERMANENT" },
  { "name": "Mandalika International Street Circuit", "country": "ID", "city": "Lombok", "type": "STREET", "lengthKm": 4.31, "openedYear": 2021 },
  { "name": "Manfeild Circuit Chris Amon", "country": "NZ", "city": "Feilding", "type": "PERMANENT" },
  { "name": "Mantorp Park", "country": "SE", "city": "Mantorp", "type": "PERMANENT" },
  { "name": "Martinsville Speedway", "country": "US", "city": "Martinsville", "type": "OVAL" },
  { "name": "Michigan International Speedway", "country": "US", "city": "Brooklyn", "type": "OVAL" },
  { "name": "Mid-Ohio Sports Car Course", "country": "US", "city": "Lexington", "type": "PERMANENT", "lengthKm": 3.634, "openedYear": 1962 },
  { "name": "Milwaukee Mile", "country": "US", "city": "West Allis", "type": "OVAL" },
  { "name": "Moscow Raceway", "country": "RU", "city": "Volokolamsk", "type": "PERMANENT" },
  { "name": "Motorsport Arena Oschersleben", "country": "DE", "city": "Oschersleben", "type": "PERMANENT" },
  { "name": "Nashville Superspeedway", "country": "US", "city": "Lebanon", "type": "OVAL" },
  { "name": "New Hampshire Motor Speedway", "country": "US", "city": "Loudon", "type": "OVAL" },
  { "name": "New Jersey Motorsports Park", "country": "US", "city": "Millville", "type": "PERMANENT" },
  { "name": "Ningbo International Speedpark", "country": "CN", "city": "Ningbo", "type": "PERMANENT" },
  { "name": "NOLA Motorsports Park", "country": "US", "city": "Avondale", "type": "PERMANENT" },
  { "name": "Norisring", "country": "DE", "city": "Nuremberg", "type": "STREET", "lengthKm": 2.3 },
  { "name": "Okayama International Circuit", "country": "JP", "city": "Mimasaka", "type": "PERMANENT" },
  { "name": "Padborg Park", "country": "DK", "city": "Padborg", "type": "PERMANENT" },
  { "name": "Pannónia Ring", "country": "HU", "city": "Ostffyasszonyfa", "type": "PERMANENT" },
  { "name": "Pembrey Circuit", "country": "GB", "city": "Llanelli", "type": "PERMANENT" },
  { "name": "Phoenix Raceway", "country": "US", "city": "Avondale", "type": "OVAL" },
  { "name": "Pocono Raceway", "country": "US", "city": "Long Pond", "type": "OVAL" },
  { "name": "Portland International Raceway", "country": "US", "city": "Portland", "type": "PERMANENT" },
  { "name": "Pukekohe Park Raceway", "country": "NZ", "city": "Pukekohe", "type": "PERMANENT" },
  { "name": "Queensland Raceway", "country": "AU", "city": "Ipswich", "type": "PERMANENT" },
  { "name": "Richmond Raceway", "country": "US", "city": "Richmond", "type": "OVAL" },
  { "name": "Ring Knutstorp", "country": "SE", "city": "Kågeröd", "type": "PERMANENT" },
  { "name": "Rudskogen Motorsenter", "country": "NO", "city": "Rakkestad", "type": "PERMANENT" },
  { "name": "Sachsenring", "country": "DE", "city": "Hohenstein-Ernstthal", "type": "PERMANENT", "lengthKm": 3.671, "openedYear": 1996 },
  { "name": "Salzburgring", "country": "AT", "city": "Salzburg", "type": "PERMANENT" },
  { "name": "Sandown Raceway", "country": "AU", "city": "Melbourne", "type": "PERMANENT" },
  { "name": "Sentul International Circuit", "country": "ID", "city": "Bogor", "type": "PERMANENT" },
  { "name": "Slovakia Ring", "country": "SK", "city": "Orechová Potôň", "type": "PERMANENT" },
  { "name": "Snetterton Circuit", "country": "GB", "city": "Norfolk", "type": "PERMANENT" },
  { "name": "Sportsland SUGO", "country": "JP", "city": "Murata", "type": "PERMANENT" },
  { "name": "Summit Point Motorsports Park", "country": "US", "city": "Summit Point", "type": "PERMANENT" },
  { "name": "Sydney Motorsport Park", "country": "AU", "city": "Sydney", "type": "PERMANENT" },
  { "name": "Symmons Plains Raceway", "country": "AU", "city": "Launceston", "type": "PERMANENT" },
  { "name": "Teretonga Park", "country": "NZ", "city": "Invercargill", "type": "PERMANENT" },
  { "name": "Texas Motor Speedway", "country": "US", "city": "Fort Worth", "type": "OVAL" },
  { "name": "The Bend Motorsport Park", "country": "AU", "city": "Tailem Bend", "type": "PERMANENT" },
  { "name": "Thermal Club", "country": "US", "city": "Thermal", "type": "PERMANENT" },
  { "name": "Thruxton Circuit", "country": "GB", "city": "Andover", "type": "PERMANENT" },
  { "name": "Tor Poznań", "country": "PL", "city": "Poznań", "type": "PERMANENT" },
  { "name": "Tsukuba Circuit", "country": "JP", "city": "Shimotsuma", "type": "PERMANENT" },
  { "name": "Utah Motorsports Campus", "country": "US", "city": "Tooele", "type": "PERMANENT" },
  { "name": "Winton Motor Raceway", "country": "AU", "city": "Winton", "type": "PERMANENT" },
  { "name": "World Wide Technology Raceway", "country": "US", "city": "Madison", "type": "OVAL" },
  { "name": "Zhuhai International Circuit", "country": "CN", "city": "Zhuhai", "type": "PERMANENT" },
  { "name": "Zwartkops Raceway", "country": "ZA", "city": "Pretoria", "type": "PERMANENT" }
]
