[
  {
    "fullName": "CrowdStrike Racing by APR",
    "shortName": "CrowdStrike APR",
    "country": "US",
    "status": "ACTIVE"
  },
  {
    "fullName": "United Autosports USA",
    "shortName": "United USA",
    "country": "US",
    "status": "ACTIVE"
  },
  {
    "fullName": "Tower Motorsports",
    "shortName": "Tower",
    "country": "US",
    "status": "ACTIVE"
  },
  {
    "fullName": "TDS Racing",
    "shortName": "TDS",
    "country": "FR",
    "status": "ACTIVE"
  },
  {
    "fullName": "Era Motorsport",
    "shortName": "Era",
    "country": "US",
    "status": "ACTIVE"
  },
  {
    "fullName": "Intersport Racing",
    "shortName": "Intersport",
    "country": "US",
    "status": "ACTIVE"
  },
  {
    "fullName": "Inter Europol Competition",
    "shortName": "Inter Europol",
    "country": "PL",
    "status": "ACTIVE"
  },
  {
    "fullName": "Bryan Herta Autosport with PR1/Mathiasen",
    "shortName": "Bryan Herta",
    "country": "US",
    "status": "ACTIVE"
  },
  {
    "fullName": "Team Tonis",
    "shortName": "Team Tonis",
    "country": "EE",
    "status": "ACTIVE"
  },
  {
    "fullName": "Pratt Miller Motorsports",
    "shortName": "Pratt Miller",
    "country": "US",
    "status": "ACTIVE"
  },
  {
    "fullName": "Triarsi Competizione",
    "shortName": "Triarsi",
    "country": "US",
    "status": "ACTIVE"
  },
  {
    "fullName": "Paul Miller Racing",
    "shortName": "Paul Miller",
    "country": "US",
    "status": "ACTIVE"
  },
  {
    "fullName": "Corvette Racing by Pratt Miller Motorsports",
    "shortName": "Corvette Racing",
    "country": "US",
    "status": "ACTIVE"
  },
  {
    "fullName": "Pfaff Motorsports",
    "shortName": "Pfaff",
    "country": "CA",
    "status": "ACTIVE"
  },
  {
    "fullName": "Vasser Sullivan Racing",
    "shortName": "Vasser Sullivan",
    "country": "US",
    "status": "ACTIVE"
  },
  {
    "fullName": "Winward Racing",
    "shortName": "Winward",
    "country": "US",
    "status": "ACTIVE"
  },
  {
    "fullName": "RLL Team McLaren",
    "shortName": "RLL McLaren",
    "country": "US",
    "status": "ACTIVE"
  },
  {
    "fullName": "Risi Competizione",
    "shortName": "Risi",
    "country": "US",
    "status": "ACTIVE"
  },
  {
    "fullName": "Ford Racing",
    "shortName": "Ford Racing",
    "country": "US",
    "status": "ACTIVE"
  },
  {
    "fullName": "AO Racing",
    "shortName": "AO Racing",
    "country": "US",
    "status": "ACTIVE"
  },
  {
    "fullName": "Manthey Racing",
    "shortName": "Manthey",
    "country": "DE",
    "status": "ACTIVE"
  },
  {
    "fullName": "13 Autosport",
    "shortName": "13 Autosport",
    "country": "CA",
    "status": "ACTIVE"
  },
  {
    "fullName": "Myers Riley Motorsports",
    "shortName": "Myers Riley",
    "country": "US",
    "status": "ACTIVE"
  },
  {
    "fullName": "van der Steur Racing",
    "shortName": "van der Steur",
    "country": "US",
    "status": "ACTIVE"
  },
  {
    "fullName": "AF Corse USA",
    "shortName": "AF Corse USA",
    "country": "US",
    "status": "ACTIVE"
  },
  {
    "fullName": "Heart of Racing Team",
    "shortName": "Heart of Racing",
    "country": "US",
    "status": "ACTIVE"
  },
  {
    "fullName": "RS1",
    "shortName": "RS1",
    "country": "US",
    "status": "ACTIVE"
  },
  {
    "fullName": "Conquest Racing",
    "shortName": "Conquest",
    "country": "US",
    "status": "ACTIVE"
  },
  {
    "fullName": "DXDT Racing",
    "shortName": "DXDT",
    "country": "US",
    "status": "ACTIVE"
  },
  {
    "fullName": "Magnus Racing",
    "shortName": "Magnus",
    "country": "US",
    "status": "ACTIVE"
  },
  {
    "fullName": "Wayne Taylor Racing",
    "shortName": "WTR",
    "country": "US",
    "status": "ACTIVE"
  },
  {
    "fullName": "Gradient Racing",
    "shortName": "Gradient",
    "country": "US",
    "status": "ACTIVE"
  },
  {
    "fullName": "Inception Racing",
    "shortName": "Inception",
    "country": "GB",
    "status": "ACTIVE"
  }
]
